setup.cfg
setup.py
coolock/Coordinator.py
coolock/__init__.py
coolock.egg-info/PKG-INFO
coolock.egg-info/SOURCES.txt
coolock.egg-info/dependency_links.txt
coolock.egg-info/requires.txt
coolock.egg-info/top_level.txt
scripts/coolock